motllo/__init__.py
motllo/build.py
motllo/main.py
motllo/markdown.py
motllo/markdown_parser.py
motllo/ops.py
motllo/traverser.py
motllo/tree_parser.py
motllo-0.2.2.dist-info/entry_points.txt
motllo-0.2.2.dist-info/LICENSE
motllo-0.2.2.dist-info/WHEEL
motllo-0.2.2.dist-info/METADATA
motllo-0.2.2.dist-info/RECORD
