Metadata-Version: 2.1
Name: motllo
Version: 0.2.2
Summary: Project patterns like I like them
Home-page: https://github.com/rberenguel/motllo
License: MIT
Author: Ruben Berenguel
Author-email: ruben+poetry@mostlymaths.net
Requires-Python: >=3.7,<4.0
Classifier: License :: OSI Approved :: MIT License
Classifier: Programming Language :: Python :: 3
Classifier: Programming Language :: Python :: 3.7
Classifier: Programming Language :: Python :: 3.8
Requires-Dist: click (>=7.1.1,<8.0.0)
Requires-Dist: colorlog (>=4.1.0,<5.0.0)
Requires-Dist: pyyaml (>=5.3,<6.0)
Project-URL: Repository, https://github.com/rberenguel/motllo
